nextgenjax/__init__.py
nextgenjax/activations.py
nextgenjax/custom_layers.py
nextgenjax/generation_capabilities.py
nextgenjax/hybrid_model.py
nextgenjax/integrations.py
nextgenjax/jax_integration.py
nextgenjax/layers.py
nextgenjax/model.py
nextgenjax/optimizers.py
nextgenjax/parallelism_example.py
nextgenjax/train.py
nextgenjax/transformer_models.py
nextgenjax/verify_compatibility.py
nextgenjax/vocab_parallel_embedding.py
nextgenjax-0.2.0.dist-info/LICENSE
nextgenjax-0.2.0.dist-info/METADATA
nextgenjax-0.2.0.dist-info/WHEEL
nextgenjax-0.2.0.dist-info/top_level.txt
nextgenjax-0.2.0.dist-info/RECORD
