Metadata-Version: 2.1
Name: nextgenjax
Version: 0.2.0
Summary: A JAX-based neural network library surpassing Google DeepMind's Haiku and Optax
Home-page: https://github.com/VishwamAI/NextGenJAX
Author: kasinadhsarma
Author-email: kasinadhsarma@gmail.com
License: MIT
Platform: UNKNOWN
Classifier: Programming Language :: Python :: 3
Classifier: Programming Language :: Python :: 3.9
Classifier: Programming Language :: Python :: 3.10
Classifier: Programming Language :: Python :: 3.11
Classifier: License :: OSI Approved :: MIT License
Classifier: Operating System :: OS Independent
Requires-Python: >=3.9
License-File: LICENSE
Requires-Dist: Pillow
Requires-Dist: chex (>=0.1.86)
Requires-Dist: dm-haiku
Requires-Dist: fairscale
Requires-Dist: flax
Requires-Dist: gym
Requires-Dist: jax
Requires-Dist: jaxlib
Requires-Dist: moviepy
Requires-Dist: numpy (>=1.24.1)
Requires-Dist: optax
Requires-Dist: scipy
Requires-Dist: stable-baselines3
Requires-Dist: sympy
Requires-Dist: tensorflow
Requires-Dist: torch
Requires-Dist: transformers (==4.38.0)
Requires-Dist: whisper
Provides-Extra: dev
Requires-Dist: flake8 (==3.9.2) ; extra == 'dev'
Requires-Dist: pytest (==6.2.4) ; extra == 'dev'
